.gitignore
CHANGES.rst
MANIFEST.in
README.rst
README.txt
setup.py
xm/__init__.py
xm.charting.egg-info/PKG-INFO
xm.charting.egg-info/SOURCES.txt
xm.charting.egg-info/dependency_links.txt
xm.charting.egg-info/entry_points.txt
xm.charting.egg-info/namespace_packages.txt
xm.charting.egg-info/not-zip-safe
xm.charting.egg-info/requires.txt
xm.charting.egg-info/top_level.txt
xm/charting/__init__.py
xm/charting/chart.txt
xm/charting/gantt.py
xm/charting/interfaces.py
xm/charting/model.py
xm/charting/tests.py