Metadata-Version: 1.0
Name: xm.charting
Version: 0.5
Summary: For generating gantt charts
Home-page: https://plone.org/products/extreme-management-tool/
Author: Rocky Burt
Author-email: rocky@serverzen.com
License: GPL
Platform: UNKNOWN
Classifier: Programming Language :: Python
Classifier: Framework :: Plone
Classifier: Framework :: Zope2
Classifier: Framework :: Zope3
Classifier: Topic :: Software Development :: Libraries :: Python Modules
